Workbook

Sheet Invoice Dispute Tracker
A1: Customer | B1: Invoice | C1: Issue (missing PO, incorrect billing, etc.) | D1: Owner | E1: Deadline (max 5 days resolution)

Sheet Ouderdomsanalyseperdebiteur
A1: CodeAdministratie | B1: NaamAdministratie | C1: CodeDebiteur | D1: NaamDebiteur | E1: Code | F1: Boekdatum | G1: Vervaldatum | H1: Factuurnummer | I1: Saldo | J1: Saldo1 | K1: 030dagen | L1: 3160dagen | M1: 6190dagen | N1: 90dagen | O1: Dagenoud | P1: Boekingsstatus
A2: RD1106 | B2: Van Noort Gassler & Co Rotterdam B.V. | C2: 1108 | D2: Van Noort Gassler & Co. 's-Gravenhage B.V. | E2: MEMO | F2: 44833 | G2: 44863 | I2: -22514.97 | J2: -22514.97 | K2: 0 | L2: 0 | M2: 0 | N2: -22514.97 | O2: =TODAY()-G2 -> 1307 | P2: Definitief
A3: RD1106 | B3: Van Noort Gassler & Co Rotterdam B.V. | C3: 1108 | D3: Van Noort Gassler & Co. 's-Gravenhage B.V. | E3: MEMO | F3: 45071 | G3: 45101 | I3: 48698.36 | J3: 48698.36 | K3: 0 | L3: 0 | M3: 0 | N3: 48698.36 | O3: =TODAY()-G3 -> 1069 | P3: Definitief
A4: RD1106 | B4: Van Noort Gassler & Co Rotterdam B.V. | C4: 1108 | D4: Van Noort Gassler & Co. 's-Gravenhage B.V. | E4: VRK | F4: 43690 | G4: 43720 | H4: R190691 | I4: 30.25 | J4: 30.25 | K4: 0 | L4: 0 | M4: 0 | N4: 30.25 | O4: =TODAY()-G4 -> 2450 | P4: Definitief
A5: RD1106 | B5: Van Noort Gassler & Co Rotterdam B.V. | C5: 1108 | D5: Van Noort Gassler & Co. 's-Gravenhage B.V. | E5: VRK | F5: 43690 | G5: 43720 | H5: R190689 | I5: 61.59 | J5: 61.59 | K5: 0 | L5: 0 | M5: 0 | N5: 61.59 | O5: =TODAY()-G5 -> 2450 | P5: Definitief
A6: RD1106 | B6: Van Noort Gassler & Co Rotterdam B.V. | C6: 1108 | D6: Van Noort Gassler & Co. 's-Gravenhage B.V. | E6: VRK | F6: 43690 | G6: 43720 | H6: R190694 | I6: 145.13 | J6: 145.13 | K6: 0 | L6: 0 | M6: 0 | N6: 145.13 | O6: =TODAY()-G6 -> 2450 | P6: Definitief
A7: RD1106 | B7: Van Noort Gassler & Co Rotterdam B.V. | C7: 1108 | D7: Van Noort Gassler & Co. 's-Gravenhage B.V. | E7: VRK | F7: 43735 | G7: 43765 | H7: R190789 | I7: 30.25 | J7: 30.25 | K7: 0 | L7: 0 | M7: 0 | N7: 30.25 | O7: =TODAY()-G7 -> 2405 | P7: Definitief
A8: RD1106 | B8: Van Noort Gassler & Co Rotterdam B.V. | C8: 1108 | D8: Van Noort Gassler & Co. 's-Gravenhage B.V. | E8: VRK | F8: 43735 | G8: 43765 | H8: R190791 | I8: 61.64 | J8: 61.64 | K8: 0 | L8: 0 | M8: 0 | N8: 61.64 | O8: =TODAY()-G8 -> 2405 | P8: Definitief
A9: RD1106 | B9: Van Noort Gassler & Co Rotterdam B.V. | C9: 1108 | D9: Van Noort Gassler & Co. 's-Gravenhage B.V. | E9: VRK | F9: 43735 | G9: 43765 | H9: R190786 | I9: 145.13 | J9: 145.13 | K9: 0 | L9: 0 | M9: 0 | N9: 145.13 | O9: =TODAY()-G9 -> 2405 | P9: Definitief
A10: RD1106 | B10: Van Noort Gassler & Co Rotterdam B.V. | C10: 1108 | D10: Van Noort Gassler & Co. 's-Gravenhage B.V. | E10: VRK | F10: 43774 | G10: 43804 | H10: R190934 | I10: 30.25 | J10: 30.25 | K10: 0 | L10: 0 | M10: 0 | N10: 30.25 | O10: =TODAY()-G10 -> 2366 | P10: Definitief
A11: RD1106 | B11: Van Noort Gassler & Co Rotterdam B.V. | C11: 1108 | D11: Van Noort Gassler & Co. 's-Gravenhage B.V. | E11: VRK | F11: 43774 | G11: 43804 | H11: R190937 | I11: 30.25 | J11: 30.25 | K11: 0 | L11: 0 | M11: 0 | N11: 30.25 | O11: =TODAY()-G11 -> 2366 | P11: Definitief
A12: RD1106 | B12: Van Noort Gassler & Co Rotterdam B.V. | C12: 1108 | D12: Van Noort Gassler & Co. 's-Gravenhage B.V. | E12: VRK | F12: 43774 | G12: 43804 | H12: R190944 | I12: 61.33 | J12: 61.33 | K12: 0 | L12: 0 | M12: 0 | N12: 61.33 | O12: =TODAY()-G12 -> 2366 | P12: Definitief
A13: RD1106 | B13: Van Noort Gassler & Co Rotterdam B.V. | C13: 1108 | D13: Van Noort Gassler & Co. 's-Gravenhage B.V. | E13: VRK | F13: 43774 | G13: 43804 | H13: R190952 | I13: 145.13 | J13: 145.13 | K13: 0 | L13: 0 | M13: 0 | N13: 145.13 | O13: =TODAY()-G13 -> 2366 | P13: Definitief
A14: RD1106 | B14: Van Noort Gassler & Co Rotterdam B.V. | C14: 1108 | D14: Van Noort Gassler & Co. 's-Gravenhage B.V. | E14: VRK | F14: 43774 | G14: 43804 | H14: R190947 | I14: 61.08 | J14: 61.08 | K14: 0 | L14: 0 | M14: 0 | N14: 61.08 | O14: =TODAY()-G14 -> 2366 | P14: Definitief
A15: RD1106 | B15: Van Noort Gassler & Co Rotterdam B.V. | C15: 1108 | D15: Van Noort Gassler & Co. 's-Gravenhage B.V. | E15: VRK | F15: 43774 | G15: 43804 | H15: R190956 | I15: 145.13 | J15: 145.13 | K15: 0 | L15: 0 | M15: 0 | N15: 145.13 | O15: =TODAY()-G15 -> 2366 | P15: Definitief
... A122: RD1106 | B122: Van Noort Gassler & Co Rotterdam B.V. | C122: 1110 | D122: Van Noort Gassler & Co. Haarlem B.V. | E122: VRK | F122: 46097 | G122: 46127 | H122: 102026-0356 | I122: 524.63 | J122: 524.63 | K122: 0 | L122: 524.63 | M122: 0 | N122: 0 | O122: =TODAY()-G122 -> 43 | P122: Concept
A123: RD1106 | B123: Van Noort Gassler & Co Rotterdam B.V. | C123: 1111 | D123: JPA Van Noort Gassler & Co B.V. | E123: BNK | F123: 45903 | G123: 45933 | I123: -90000 | J123: -90000 | K123: 0 | L123: 0 | M123: 0 | N123: -90000 | O123: =TODAY()-G123 -> 237 | P123: Concept
A124: RD1106 | B124: Van Noort Gassler & Co Rotterdam B.V. | C124: 1111 | D124: JPA Van Noort Gassler & Co B.V. | E124: BNK | F124: 46098 | G124: 46128 | I124: -60000 | J124: -60000 | K124: 0 | L124: -60000 | M124: 0 | N124: 0 | O124: =TODAY()-G124 -> 42 | P124: Concept
A125: RD1106 | B125: Van Noort Gassler & Co Rotterdam B.V. | C125: 1111 | D125: JPA Van Noort Gassler & Co B.V. | E125: MEMO | F125: 45835 | G125: 45865 | I125: -218713 | J125: -218713 | K125: 0 | L125: 0 | M125: 0 | N125: -218713 | O125: =TODAY()-G125 -> 305 | P125: Concept
A126: RD1106 | B126: Van Noort Gassler & Co Rotterdam B.V. | C126: 1111 | D126: JPA Van Noort Gassler & Co B.V. | E126: MEMO | F126: 45989 | G126: 46019 | I126: -277509.26 | J126: -277509.26 | K126: 0 | L126: 0 | M126: 0 | N126: -277509.26 | O126: =TODAY()-G126 -> 151 | P126: Concept
A127: RD1106 | B127: Van Noort Gassler & Co Rotterdam B.V. | C127: 1111 | D127: JPA Van Noort Gassler & Co B.V. | E127: VRK | F127: 45448 | G127: 45478 | H127: 102025-0795 | I127: 21600 | J127: 21600 | K127: 0 | L127: 0 | M127: 0 | N127: 21600 | O127: =TODAY()-G127 -> 692 | P127: Concept
A128: RD1106 | B128: Van Noort Gassler & Co Rotterdam B.V. | C128: 1111 | D128: JPA Van Noort Gassler & Co B.V. | E128: VRK | F128: 45461 | G128: 45491 | H128: 2024-0669 | I128: 75957.75 | J128: 45540.44 | K128: 0 | L128: 0 | M128: 0 | N128: 45540.44 | O128: =TODAY()-G128 -> 679 | P128: Concept
A129: RD1106 | B129: Van Noort Gassler & Co Rotterdam B.V. | C129: 1111 | D129: JPA Van Noort Gassler & Co B.V. | E129: VRK | F129: 45470 | G129: 45500 | H129: 2024-0670 | I129: 64595.11 | J129: 64595.11 | K129: 0 | L129: 0 | M129: 0 | N129: 64595.11 | O129: =TODAY()-G129 -> 670 | P129: Concept
A130: RD1106 | B130: Van Noort Gassler & Co Rotterdam B.V. | C130: 1111 | D130: JPA Van Noort Gassler & Co B.V. | E130: VRK | F130: 45475 | G130: 45505 | H130: 2024-0672 | I130: 63218.87 | J130: 63218.87 | K130: 0 | L130: 0 | M130: 0 | N130: 63218.87 | O130: =TODAY()-G130 -> 665 | P130: Concept
A131: RD1106 | B131: Van Noort Gassler & Co Rotterdam B.V. | C131: 1111 | D131: JPA Van Noort Gassler & Co B.V. | E131: VRK | F131: 45482 | G131: 45512 | H131: 2024-0787 | I131: -25155.9 | J131: -25155.9 | K131: 0 | L131: 0 | M131: 0 | N131: -25155.9 | O131: =TODAY()-G131 -> 658 | P131: Concept
A132: RD1106 | B132: Van Noort Gassler & Co Rotterdam B.V. | C132: 1111 | D132: JPA Van Noort Gassler & Co B.V. | E132: VRK | F132: 45482 | G132: 45512 | H132: 2024-0788 | I132: 19602 | J132: 19602 | K132: 0 | L132: 0 | M132: 0 | N132: 19602 | O132: =TODAY()-G132 -> 658 | P132: Concept
A133: RD1106 | B133: Van Noort Gassler & Co Rotterdam B.V. | C133: 1111 | D133: JPA Van Noort Gassler & Co B.V. | E133: VRK | F133: 45506 | G133: 45536 | H133: 2024-0813 | I133: 1815 | J133: 1815 | K133: 0 | L133: 0 | M133: 0 | N133: 1815 | O133: =TODAY()-G133 -> 634 | P133: Concept
A134: RD1106 | B134: Van Noort Gassler & Co Rotterdam B.V. | C134: 1111 | D134: JPA Van Noort Gassler & Co B.V. | E134: VRK | F134: 45509 | G134: 45539 | H134: 2024-0814 | I134: 21845.34 | J134: 21845.34 | K134: 0 | L134: 0 | M134: 0 | N134: 21845.34 | O134: =TODAY()-G134 -> 631 | P134: Concept
A135: RD1106 | B135: Van Noort Gassler & Co Rotterdam B.V. | C135: 1111 | D135: JPA Van Noort Gassler & Co B.V. | E135: VRK | F135: 45509 | G135: 45539 | H135: 2024-0815 | I135: 32365.83 | J135: 32365.83 | K135: 0 | L135: 0 | M135: 0 | N135: 32365.83 | O135: =TODAY()-G135 -> 631 | P135: Concept
A136: RD1106 | B136: Van Noort Gassler & Co Rotterdam B.V. | C136: 1111 | D136: JPA Van Noort Gassler & Co B.V. | E136: VRK | F136: 45519 | G136: 45549 | H136: 2024-0910 | I136: 3539.25 | J136: 3539.25 | K136: 0 | L136: 0 | M136: 0 | N136: 3539.25 | O136: =TODAY()-G136 -> 621 | P136: Concept
A137: RD1106 | B137: Van Noort Gassler & Co Rotterdam B.V. | C137: 1111 | D137: JPA Van Noort Gassler & Co B.V. | E137: VRK | F137: 45530 | G137: 45560 | H137: 2024-0917 | I137: 33215.09 | J137: 33215.09 | K137: 0 | L137: 0 | M137: 0 | N137: 33215.09 | O137: =TODAY()-G137 -> 610 | P137: Concept
A138: RD1106 | B138: Van Noort Gassler & Co Rotterdam B.V. | C138: 1111 | D138: JPA Van Noort Gassler & Co B.V. | E138: VRK | F138: 45530 | G138: 45560 | H138: 2024-0916 | I138: 16694.41 | J138: 16694.41 | K138: 0 | L138: 0 | M138: 0 | N138: 16694.41 | O138: =TODAY()-G138 -> 610 | P138: Concept
... A273: RD1106 | B273: Van Noort Gassler & Co Rotterdam B.V. | C273: 1295 | D273: Patrick van Gils Beheer B.V. | E273: VRK | F273: 46118 | G273: 46148 | H273: 102026-0517 | I273: 79.86 | J273: 79.86 | K273: 79.86 | L273: 0 | M273: 0 | N273: 0 | O273: =TODAY()-G273 -> 22 | P273: Concept
A274: RD1106 | B274: Van Noort Gassler & Co Rotterdam B.V. | C274: 1312 | D274: NEVE Trans B.V. | E274: BNK | F274: 45951 | G274: 45981 | I274: 361.77 | J274: 361.77 | K274: 0 | L274: 0 | M274: 0 | N274: 361.77 | O274: =TODAY()-G274 -> 189 | P274: Concept
A275: RD1106 | B275: Van Noort Gassler & Co Rotterdam B.V. | C275: 1337 | D275: Kraskino Consultants Ltd. | E275: VRK | F275: 44796 | G275: 44826 | H275: 2022-0759 | I275: 1725.26 | J275: 1725.26 | K275: 0 | L275: 0 | M275: 0 | N275: 1725.26 | O275: =TODAY()-G275 -> 1344 | P275: Definitief
A276: RD1106 | B276: Van Noort Gassler & Co Rotterdam B.V. | C276: 1410 | D276: Stichting Studeren/Werken op Maat | E276: BNK | F276: 45699 | G276: 45729 | I276: -242 | J276: -242 | K276: 0 | L276: 0 | M276: 0 | N276: -242 | O276: =TODAY()-G276 -> 441 | P276: Concept
A277: RD1106 | B277: Van Noort Gassler & Co Rotterdam B.V. | C277: 1410 | D277: Stichting Studeren/Werken op Maat | E277: VRK | F277: 45966 | G277: 45996 | H277: 102025-1105 | I277: 9965.26 | J277: 9965.26 | K277: 0 | L277: 0 | M277: 0 | N277: 9965.26 | O277: =TODAY()-G277 -> 174 | P277: Concept
A278: RD1106 | B278: Van Noort Gassler & Co Rotterdam B.V. | C278: 1410 | D278: Stichting Studeren/Werken op Maat | E278: VRK | F278: 46055 | G278: 46085 | H278: 102026-0248 | I278: 3297.25 | J278: 3297.25 | K278: 0 | L278: 0 | M278: 3297.25 | N278: 0 | O278: =TODAY()-G278 -> 85 | P278: Concept
A279: RD1106 | B279: Van Noort Gassler & Co Rotterdam B.V. | C279: 1410 | D279: Stichting Studeren/Werken op Maat | E279: VRK | F279: 46083 | G279: 46113 | H279: 102026-0420 | I279: 3297.25 | J279: 3297.25 | K279: 0 | L279: 3297.25 | M279: 0 | N279: 0 | O279: =TODAY()-G279 -> 57 | P279: Concept
A280: RD1106 | B280: Van Noort Gassler & Co Rotterdam B.V. | C280: 1410 | D280: Stichting Studeren/Werken op Maat | E280: VRK | F280: 46113 | G280: 46143 | H280: 102026-0544 | I280: 3297.25 | J280: 3297.25 | K280: 3297.25 | L280: 0 | M280: 0 | N280: 0 | O280: =TODAY()-G280 -> 27 | P280: Concept
A281: RD1106 | B281: Van Noort Gassler & Co Rotterdam B.V. | C281: 1410 | D281: Stichting Studeren/Werken op Maat | E281: VRK | F281: 46118 | G281: 46148 | H281: 102026-0423 | I281: 574.75 | J281: 574.75 | K281: 574.75 | L281: 0 | M281: 0 | N281: 0 | O281: =TODAY()-G281 -> 22 | P281: Concept
A282: RD1106 | B282: Van Noort Gassler & Co Rotterdam B.V. | C282: 1420 | D282: Stichting Werken Op Maat. | E282: VRK | F282: 46031 | G282: 46061 | H282: 102026-0118 | I282: 3297.25 | J282: 3297.25 | K282: 0 | L282: 0 | M282: 0 | N282: 3297.25 | O282: =TODAY()-G282 -> 109 | P282: Concept
A283: RD1106 | B283: Van Noort Gassler & Co Rotterdam B.V. | C283: 1420 | D283: Stichting Werken Op Maat. | E283: VRK | F283: 46034 | G283: 46064 | H283: 102026-0122 | I283: -3297.25 | J283: -3297.25 | K283: 0 | L283: 0 | M283: 0 | N283: -3297.25 | O283: =TODAY()-G283 -> 106 | P283: Concept
A284: RD1106 | B284: Van Noort Gassler & Co Rotterdam B.V. | C284: 1420 | D284: Stichting Werken Op Maat. | E284: VRK | F284: 46055 | G284: 46085 | H284: 102026-0163 | I284: 1028.5 | J284: 1028.5 | K284: 0 | L284: 0 | M284: 1028.5 | N284: 0 | O284: =TODAY()-G284 -> 85 | P284: Concept
A285: RD1106 | B285: Van Noort Gassler & Co Rotterdam B.V. | C285: 1420 | D285: Stichting Werken Op Maat. | E285: VRK | F285: 46055 | G285: 46085 | H285: 102026-0225 | I285: 19.12 | J285: 19.12 | K285: 0 | L285: 0 | M285: 19.12 | N285: 0 | O285: =TODAY()-G285 -> 85 | P285: Concept
A286: RD1106 | B286: Van Noort Gassler & Co Rotterdam B.V. | C286: 1420 | D286: Stichting Werken Op Maat. | E286: VRK | F286: 46064 | G286: 46094 | H286: 102026-0237 | I286: -1028.5 | J286: -1028.5 | K286: 0 | L286: 0 | M286: -1028.5 | N286: 0 | O286: =TODAY()-G286 -> 76 | P286: Concept
A287: RD1106 | B287: Van Noort Gassler & Co Rotterdam B.V. | C287: 1420 | D287: Stichting Werken Op Maat. | E287: VRK | F287: 46064 | G287: 46094 | H287: 102026-0238 | I287: -19.12 | J287: -19.12 | K287: 0 | L287: 0 | M287: -19.12 | N287: 0 | O287: =TODAY()-G287 -> 76 | P287: Concept
A288: RD1106 | B288: Van Noort Gassler & Co Rotterdam B.V. | C288: 1420 | D288: Stichting Werken Op Maat. | E288: VRK | F288: 46118 | G288: 46148 | H288: 102026-0475 | I288: 1028.5 | J288: 1028.5 | K288: 1028.5 | L288: 0 | M288: 0 | N288: 0 | O288: =TODAY()-G288 -> 22 | P288: Concept
... A377: RD1106 | B377: Van Noort Gassler & Co Rotterdam B.V. | C377: 1613 | D377: Knowdis B.V. | E377: VRK | F377: 46030 | G377: 46120 | H377: 102026-0040 | I377: 415.94 | J377: 415.94 | K377: 0 | L377: 415.94 | M377: 0 | N377: 0 | O377: =TODAY()-G377 -> 50 | P377: Concept
A378: RD1106 | B378: Van Noort Gassler & Co Rotterdam B.V. | C378: 1616 | D378: TOFF concept | E378: MEMO | F378: 44927 | G378: 44957 | I378: 180.29 | J378: 23.64 | K378: 0 | L378: 0 | M378: 0 | N378: 23.64 | O378: =TODAY()-G378 -> 1213 | P378: Definitief
A379: RD1106 | B379: Van Noort Gassler & Co Rotterdam B.V. | C379: 1616 | D379: TOFF concept | E379: VRK | F379: 44942 | G379: 44956 | H379: 2023-0044 | I379: 211.75 | J379: 211.75 | K379: 0 | L379: 0 | M379: 0 | N379: 211.75 | O379: =TODAY()-G379 -> 1214 | P379: Definitief
A380: RD1106 | B380: Van Noort Gassler & Co Rotterdam B.V. | C380: 1616 | D380: TOFF concept | E380: VRK | F380: 44965 | G380: 44979 | H380: 2023-0165 | I380: 211.75 | J380: 211.75 | K380: 0 | L380: 0 | M380: 0 | N380: 211.75 | O380: =TODAY()-G380 -> 1191 | P380: Definitief
A381: RD1106 | B381: Van Noort Gassler & Co Rotterdam B.V. | C381: 1616 | D381: TOFF concept | E381: VRK | F381: 44991 | G381: 45005 | H381: 2023-0279 | I381: 211.75 | J381: 211.75 | K381: 0 | L381: 0 | M381: 0 | N381: 211.75 | O381: =TODAY()-G381 -> 1165 | P381: Definitief
A382: RD1106 | B382: Van Noort Gassler & Co Rotterdam B.V. | C382: 1616 | D382: TOFF concept | E382: VRK | F382: 45020 | G382: 45034 | H382: 2023-0393 | I382: 211.75 | J382: 211.75 | K382: 0 | L382: 0 | M382: 0 | N382: 211.75 | O382: =TODAY()-G382 -> 1136 | P382: Definitief
A383: RD1106 | B383: Van Noort Gassler & Co Rotterdam B.V. | C383: 1616 | D383: TOFF concept | E383: VRK | F383: 45048 | G383: 45062 | H383: 2023-0503 | I383: 211.75 | J383: 211.75 | K383: 0 | L383: 0 | M383: 0 | N383: 211.75 | O383: =TODAY()-G383 -> 1108 | P383: Definitief
A384: RD1106 | B384: Van Noort Gassler & Co Rotterdam B.V. | C384: 1616 | D384: TOFF concept | E384: VRK | F384: 45082 | G384: 45096 | H384: 2023-0594 | I384: 211.75 | J384: 211.75 | K384: 0 | L384: 0 | M384: 0 | N384: 211.75 | O384: =TODAY()-G384 -> 1074 | P384: Definitief
A385: RD1106 | B385: Van Noort Gassler & Co Rotterdam B.V. | C385: 1616 | D385: TOFF concept | E385: VRK | F385: 45110 | G385: 45124 | H385: 2023-0718 | I385: 242 | J385: 242 | K385: 0 | L385: 0 | M385: 0 | N385: 242 | O385: =TODAY()-G385 -> 1046 | P385: Definitief
A386: RD1106 | B386: Van Noort Gassler & Co Rotterdam B.V. | C386: 1616 | D386: TOFF concept | E386: VRK | F386: 45141 | G386: 45155 | H386: 2023-0836 | I386: 242 | J386: 242 | K386: 0 | L386: 0 | M386: 0 | N386: 242 | O386: =TODAY()-G386 -> 1015 | P386: Definitief
A387: RD1106 | B387: Van Noort Gassler & Co Rotterdam B.V. | C387: 1616 | D387: TOFF concept | E387: VRK | F387: 45174 | G387: 45188 | H387: 2023-0911 | I387: 242 | J387: 242 | K387: 0 | L387: 0 | M387: 0 | N387: 242 | O387: =TODAY()-G387 -> 982 | P387: Definitief
A388: RD1106 | B388: Van Noort Gassler & Co Rotterdam B.V. | C388: 1616 | D388: TOFF concept | E388: VRK | F388: 45202 | G388: 45216 | H388: 2023-1053 | I388: 242 | J388: 242 | K388: 0 | L388: 0 | M388: 0 | N388: 242 | O388: =TODAY()-G388 -> 954 | P388: Definitief
A389: RD1106 | B389: Van Noort Gassler & Co Rotterdam B.V. | C389: 1616 | D389: TOFF concept | E389: VRK | F389: 45237 | G389: 45251 | H389: 2023-1184 | I389: 242 | J389: 242 | K389: 0 | L389: 0 | M389: 0 | N389: 242 | O389: =TODAY()-G389 -> 919 | P389: Definitief
A390: RD1106 | B390: Van Noort Gassler & Co Rotterdam B.V. | C390: 1616 | D390: TOFF concept | E390: VRK | F390: 45265 | G390: 45279 | H390: 2023-1282 | I390: 242 | J390: 242 | K390: 0 | L390: 0 | M390: 0 | N390: 242 | O390: =TODAY()-G390 -> 891 | P390: Definitief
... A613: RD1106 | B613: Van Noort Gassler & Co Rotterdam B.V. | C613: 1697 | D613: Bats | E613: VRK | F613: 45691 | G613: 45705 | H613: 2025-0154 | I613: 363 | J613: 363 | K613: 0 | L613: 0 | M613: 0 | N613: 363 | O613: =TODAY()-G613 -> 465 | P613: Concept
A614: RD1106 | B614: Van Noort Gassler & Co Rotterdam B.V. | C614: 1720 | D614: Du Cap | E614: MEMO | F614: 45657 | G614: 45687 | I614: -3710.5 | J614: -3710.5 | K614: 0 | L614: 0 | M614: 0 | N614: -3710.5 | O614: =TODAY()-G614 -> 483 | P614: Concept
A615: RD1106 | B615: Van Noort Gassler & Co Rotterdam B.V. | C615: 1720 | D615: Du Cap | E615: MEMO | F615: 46022 | G615: 46052 | I615: -539.5 | J615: -539.5 | K615: 0 | L615: 0 | M615: 0 | N615: -539.5 | O615: =TODAY()-G615 -> 118 | P615: Concept
A616: RD1106 | B616: Van Noort Gassler & Co Rotterdam B.V. | C616: 1726 | D616: FTOU B.V. | E616: VRK | F616: 44110 | G616: 44140 | H616: 2020-0887 | I616: 240.79 | J616: 130.07 | K616: 0 | L616: 0 | M616: 0 | N616: 130.07 | O616: =TODAY()-G616 -> 2030 | P616: Definitief
A617: RD1106 | B617: Van Noort Gassler & Co Rotterdam B.V. | C617: 1726 | D617: FTOU B.V. | E617: VRK | F617: 44138 | G617: 44168 | H617: 2020-0997 | I617: 240.79 | J617: 240.79 | K617: 0 | L617: 0 | M617: 0 | N617: 240.79 | O617: =TODAY()-G617 -> 2002 | P617: Definitief
A618: RD1106 | B618: Van Noort Gassler & Co Rotterdam B.V. | C618: 1726 | D618: FTOU B.V. | E618: VRK | F618: 44166 | G618: 44196 | H618: 2020-1114 | I618: 240.79 | J618: 240.79 | K618: 0 | L618: 0 | M618: 0 | N618: 240.79 | O618: =TODAY()-G618 -> 1974 | P618: Definitief
A619: RD1106 | B619: Van Noort Gassler & Co Rotterdam B.V. | C619: 1726 | D619: FTOU B.V. | E619: VRK | F619: 44203 | G619: 44233 | H619: 2021-0028 | I619: 240.79 | J619: 240.79 | K619: 0 | L619: 0 | M619: 0 | N619: 240.79 | O619: =TODAY()-G619 -> 1937 | P619: Definitief
A620: RD1106 | B620: Van Noort Gassler & Co Rotterdam B.V. | C620: 1726 | D620: FTOU B.V. | E620: VRK | F620: 44243 | G620: 44273 | H620: 2021-0183 | I620: 240.79 | J620: 240.79 | K620: 0 | L620: 0 | M620: 0 | N620: 240.79 | O620: =TODAY()-G620 -> 1897 | P620: Definitief
A621: RD1106 | B621: Van Noort Gassler & Co Rotterdam B.V. | C621: 1726 | D621: FTOU B.V. | E621: VRK | F621: 44257 | G621: 44287 | H621: 2021-0260 | I621: 240.79 | J621: 240.79 | K621: 0 | L621: 0 | M621: 0 | N621: 240.79 | O621: =TODAY()-G621 -> 1883 | P621: Definitief
A622: RD1106 | B622: Van Noort Gassler & Co Rotterdam B.V. | C622: 1726 | D622: FTOU B.V. | E622: VRK | F622: 44285 | G622: 44315 | H622: 2021-0351 | I622: 240.79 | J622: 240.79 | K622: 0 | L622: 0 | M622: 0 | N622: 240.79 | O622: =TODAY()-G622 -> 1855 | P622: Definitief
A623: RD1106 | B623: Van Noort Gassler & Co Rotterdam B.V. | C623: 1726 | D623: FTOU B.V. | E623: VRK | F623: 44350 | G623: 44380 | H623: 2021-0596 | I623: 24.2 | J623: 24.2 | K623: 0 | L623: 0 | M623: 0 | N623: 24.2 | O623: =TODAY()-G623 -> 1790 | P623: Definitief
A624: RD1106 | B624: Van Noort Gassler & Co Rotterdam B.V. | C624: 1762 | D624: Z & S Sales and Marketing B.V. | E624: VRK | F624: 42948 | G624: 42978 | H624: R170267 | I624: 3708.68 | J624: 2571.33 | K624: 0 | L624: 0 | M624: 0 | N624: 2571.33 | O624: =TODAY()-G624 -> 3192 | P624: Definitief
A625: RD1106 | B625: Van Noort Gassler & Co Rotterdam B.V. | C625: 1783 | D625: Ray Consultancy B.V. | E625: VRK | F625: 43679 | G625: 43709 | H625: R190684 | I625: 4640.37 | J625: 4640.37 | K625: 0 | L625: 0 | M625: 0 | N625: 4640.37 | O625: =TODAY()-G625 -> 2461 | P625: Definitief
A626: RD1106 | B626: Van Noort Gassler & Co Rotterdam B.V. | C626: 1859 | D626: Rob Hotting Art & Concept | E626: VRK | F626: 45048 | G626: 45062 | H626: 2023-0528 | I626: 180.29 | J626: 180.29 | K626: 0 | L626: 0 | M626: 0 | N626: 180.29 | O626: =TODAY()-G626 -> 1108 | P626: Definitief
A627: RD1106 | B627: Van Noort Gassler & Co Rotterdam B.V. | C627: 1859 | D627: Rob Hotting Art & Concept | E627: VRK | F627: 45082 | G627: 45096 | H627: 2023-0619 | I627: 180.29 | J627: 180.29 | K627: 0 | L627: 0 | M627: 0 | N627: 180.29 | O627: =TODAY()-G627 -> 1074 | P627: Definitief
... A690: RD1106 | B690: Van Noort Gassler & Co Rotterdam B.V. | C690: 1983 | D690: VOF T.H. Thio en T.H. Thio-Ong | E690: VRK | F690: 46094 | G690: 46124 | H690: 102026-0354 | I690: 544.5 | J690: 544.5 | K690: 0 | L690: 544.5 | M690: 0 | N690: 0 | O690: =TODAY()-G690 -> 46 | P690: Concept
A691: RD1106 | B691: Van Noort Gassler & Co Rotterdam B.V. | C691: RD4132 | D691: Stichting Micu Zuidwest Nederland | E691: BNK | F691: 45838 | G691: 45868 | I691: -19360 | J691: -19360 | K691: 0 | L691: 0 | M691: 0 | N691: -19360 | O691: =TODAY()-G691 -> 302 | P691: Concept
A692: RD1106 | B692: Van Noort Gassler & Co Rotterdam B.V. | C692: RD4132 | D692: Stichting Micu Zuidwest Nederland | E692: BNK | F692: 45838 | G692: 45868 | I692: -17545 | J692: -17545 | K692: 0 | L692: 0 | M692: 0 | N692: -17545 | O692: =TODAY()-G692 -> 302 | P692: Concept
A693: RD1106 | B693: Van Noort Gassler & Co Rotterdam B.V. | C693: RD4530 | D693: Tradeplus24 Nederland B.V. | E693: VRK | F693: 46062 | G693: 46092 | H693: 102026-0235 | I693: 484 | J693: 484 | K693: 0 | L693: 0 | M693: 484 | N693: 0 | O693: =TODAY()-G693 -> 78 | P693: Concept
A694: RD1106 | B694: Van Noort Gassler & Co Rotterdam B.V. | C694: RD4531 | D694: NL Working Capital B.V. | E694: VRK | F694: 46062 | G694: 46092 | H694: 102026-0234 | I694: 484 | J694: 484 | K694: 0 | L694: 0 | M694: 484 | N694: 0 | O694: =TODAY()-G694 -> 78 | P694: Concept
A695: RD1106 | B695: Van Noort Gassler & Co Rotterdam B.V. | C695: RD4533 | D695: Levels Diagnostics B.V. | E695: VRK | F695: 46125 | G695: 46155 | H695: 102026-0536 | I695: 5747.5 | J695: 5747.5 | K695: 5747.5 | L695: 0 | M695: 0 | N695: 0 | O695: =TODAY()-G695 -> 15 | P695: Concept
A696: RD1106 | B696: Van Noort Gassler & Co Rotterdam B.V. | C696: RD4742 | D696: Elm Finance B.V. | E696: VRK | F696: 45488 | G696: 45518 | H696: 2024-0795 | I696: 1573 | J696: 1573 | K696: 0 | L696: 0 | M696: 0 | N696: 1573 | O696: =TODAY()-G696 -> 652 | P696: Concept
A697: RD1106 | B697: Van Noort Gassler & Co Rotterdam B.V. | C697: RD4742 | D697: Elm Finance B.V. | E697: VRK | F697: 46009 | G697: 46039 | H697: 102025-1311 | I697: -1573 | J697: -1573 | K697: 0 | L697: 0 | M697: 0 | N697: -1573 | O697: =TODAY()-G697 -> 131 | P697: Concept
A698: RD1106 | B698: Van Noort Gassler & Co Rotterdam B.V. | C698: RD4748 | D698: LUKOIL International Upstream Holdings B.V. | E698: VRK | F698: 46009 | G698: 46039 | H698: 102025-1312 | I698: 28645.24 | J698: 28645.24 | K698: 0 | L698: 0 | M698: 0 | N698: 28645.24 | O698: =TODAY()-G698 -> 131 | P698: Concept
A699: RD1106 | B699: Van Noort Gassler & Co Rotterdam B.V. | C699: RD5077 | D699: Troodos Services International B.V. | E699: VRK | F699: 45572 | G699: 45602 | H699: 2024-1024 | I699: 907.5 | J699: 907.5 | K699: 0 | L699: 0 | M699: 0 | N699: 907.5 | O699: =TODAY()-G699 -> 568 | P699: Concept
A700: RD1106 | B700: Van Noort Gassler & Co Rotterdam B.V. | C700: RD5077 | D700: Troodos Services International B.V. | E700: VRK | F700: 45572 | G700: 45602 | H700: 2024-1025 | I700: 907.5 | J700: 907.5 | K700: 0 | L700: 0 | M700: 0 | N700: 907.5 | O700: =TODAY()-G700 -> 568 | P700: Concept
A701: RD1106 | B701: Van Noort Gassler & Co Rotterdam B.V. | C701: RD5077 | D701: Troodos Services International B.V. | E701: VRK | F701: 46009 | G701: 46039 | H701: 102025-1308 | I701: -907.5 | J701: -907.5 | K701: 0 | L701: 0 | M701: 0 | N701: -907.5 | O701: =TODAY()-G701 -> 131 | P701: Concept
A702: RD1106 | B702: Van Noort Gassler & Co Rotterdam B.V. | C702: RD5077 | D702: Troodos Services International B.V. | E702: VRK | F702: 46009 | G702: 46039 | H702: 102025-1309 | I702: -907.5 | J702: -907.5 | K702: 0 | L702: 0 | M702: 0 | N702: -907.5 | O702: =TODAY()-G702 -> 131 | P702: Concept
A703: RD1106 | B703: Van Noort Gassler & Co Rotterdam B.V. | C703: RD5079 | D703: Kumkol Restructuring B.V. | E703: VRK | F703: 45572 | G703: 45602 | H703: 2024-1137 | I703: 907.5 | J703: 907.5 | K703: 0 | L703: 0 | M703: 0 | N703: 907.5 | O703: =TODAY()-G703 -> 568 | P703: Concept
A704: RD1106 | B704: Van Noort Gassler & Co Rotterdam B.V. | C704: RD5079 | D704: Kumkol Restructuring B.V. | E704: VRK | F704: 46009 | G704: 46039 | H704: 102025-1310 | I704: -907.5 | J704: -907.5 | K704: 0 | L704: 0 | M704: 0 | N704: -907.5 | O704: =TODAY()-G704 -> 131 | P704: Concept
... A721: RD1106 | B721: Van Noort Gassler & Co Rotterdam B.V. | C721: RD5339 | D721: Werken op Maat B.V. | E721: VRK | F721: 45672 | G721: 45702 | H721: 2025-0056 | I721: 242 | J721: 242 | K721: 0 | L721: 0 | M721: 0 | N721: 242 | O721: =TODAY()-G721 -> 468 | P721: Concept
A722: RD1106 | B722: Van Noort Gassler & Co Rotterdam B.V. | C722: RD5421 | D722: Coffeeshop Dizzy Duck B.V. | E722: BNK | F722: 45295 | G722: 45325 | I722: -514.25 | J722: -514.25 | K722: 0 | L722: 0 | M722: 0 | N722: -514.25 | O722: =TODAY()-G722 -> 845 | P722: Concept
A723: RD1106 | B723: Van Noort Gassler & Co Rotterdam B.V. | C723: RD5421 | D723: Coffeeshop Dizzy Duck B.V. | E723: BNK | F723: 45336 | G723: 45366 | I723: -514.25 | J723: -514.25 | K723: 0 | L723: 0 | M723: 0 | N723: -514.25 | O723: =TODAY()-G723 -> 804 | P723: Concept
A724: RD1106 | B724: Van Noort Gassler & Co Rotterdam B.V. | C724: RD5423 | D724: Duckies B.V. | E724: VRK | F724: 45726 | G724: 45756 | H724: 2025-0334 | I724: 9011.72 | J724: 9011.72 | K724: 0 | L724: 0 | M724: 0 | N724: 9011.72 | O724: =TODAY()-G724 -> 414 | P724: Concept
A725: RD1106 | B725: Van Noort Gassler & Co Rotterdam B.V. | C725: RD5423 | D725: Duckies B.V. | E725: VRK | F725: 45826 | G725: 45856 | H725: 102025-0672 | I725: -241.76 | J725: -241.76 | K725: 0 | L725: 0 | M725: 0 | N725: -241.76 | O725: =TODAY()-G725 -> 314 | P725: Concept
A726: RD1106 | B726: Van Noort Gassler & Co Rotterdam B.V. | C726: RD5423 | D726: Duckies B.V. | E726: VRK | F726: 46104 | G726: 46134 | H726: 102026-0367 | I726: 9825.56 | J726: 9825.56 | K726: 0 | L726: 9825.56 | M726: 0 | N726: 0 | O726: =TODAY()-G726 -> 36 | P726: Concept
A727: RD1106 | B727: Van Noort Gassler & Co Rotterdam B.V. | C727: RD5424 | D727: Auroria Pecunia B.V. | E727: VRK | F727: 45237 | G727: 45267 | H727: 2023-1142 | I727: 217.8 | J727: 217.8 | K727: 0 | L727: 0 | M727: 0 | N727: 217.8 | O727: =TODAY()-G727 -> 903 | P727: Definitief
A728: RD1106 | B728: Van Noort Gassler & Co Rotterdam B.V. | C728: RD5424 | D728: Auroria Pecunia B.V. | E728: VRK | F728: 45265 | G728: 45295 | H728: 2023-1239 | I728: 217.8 | J728: 217.8 | K728: 0 | L728: 0 | M728: 0 | N728: 217.8 | O728: =TODAY()-G728 -> 875 | P728: Definitief
...

Sheet Aging breakdown
E1: Data
A2: NaamDebiteur | B2: Factuurnummer | C2: Vervaldatum | D2: Dagenoud | E2: Sum of Saldo1 | F2: Sum of 030dagen | G2: Sum of 3160dagen | H2: Sum of 6190dagen | I2: Sum of 90dagen
A3: A.J.F. Jansen B.V. | B3: 2025-0240 | C3: 45742 | D3: 428 | E3: 3646.64 | F3: 0 | G3: 0 | H3: 0 | I3: 3646.64
A4: A.J.F. Jansen B.V. Total | E4: 3646.64 | F4: 0 | G4: 0 | H4: 0 | I4: 3646.64
A5: AirFlow Luchtkanalen B.V. | B5: 102026-0361 | C5: 46118 | D5: 52 | E5: 605 | F5: 0 | G5: 605 | H5: 0 | I5: 0
B6: 102026-0501 | C6: 46132 | D6: 38 | E6: 272.25 | F6: 0 | G6: 272.25 | H6: 0 | I6: 0
B7: 102026-0648 | C7: 46162 | D7: 8 | E7: 272.25 | F7: 272.25 | G7: 0 | H7: 0 | I7: 0
B8: 2024-0226 | C8: 45369 | D8: 801 | E8: 666.12 | F8: 0 | G8: 0 | H8: 0 | I8: 666.12
B9: 2025-0330 | C9: 45740 | D9: 430 | E9: 2964.26 | F9: 0 | G9: 0 | H9: 0 | I9: 2964.26
A10: AirFlow Luchtkanalen B.V. Total | E10: 4779.88 | F10: 272.25 | G10: 877.25 | H10: 0 | I10: 3630.38
A11: American Soulfood | B11: 2020-0006 | C11: 43895 | D11: 2275 | E11: 338.8 | F11: 0 | G11: 0 | H11: 0 | I11: 338.8
B12: 2020-0114 | C12: 43895 | D12: 2275 | E12: 338.8 | F12: 0 | G12: 0 | H12: 0 | I12: 338.8
B13: 2020-0213 | E13: 338.8 | F13: 0 | G13: 0 | H13: 0 | I13: 338.8
B14: 2020-0324 | C14: 43958 | D14: 2212 | E14: 338.8 | F14: 0 | G14: 0 | H14: 0 | I14: 338.8
B15: 2020-0483 | C15: 43987 | D15: 2183 | E15: 338.8 | F15: 0 | G15: 0 | H15: 0 | I15: 338.8
B16: 2020-0536 | C16: 44014 | D16: 2156 | E16: 338.8 | F16: 0 | G16: 0 | H16: 0 | I16: 338.8
B17: 2020-0610 | C17: 44043 | D17: 2127 | E17: 338.8 | F17: 0 | G17: 0 | H17: 0 | I17: 338.8
B18: 2020-0718 | C18: 44077 | D18: 2093 | E18: 338.8 | F18: 0 | G18: 0 | H18: 0 | I18: 338.8
B19: 2020-0796 | C19: 44105 | D19: 2065 | E19: 338.8 | F19: 0 | G19: 0 | H19: 0 | I19: 338.8
B20: 2020-0874 | C20: 44140 | D20: 2030 | E20: 338.8 | F20: 0 | G20: 0 | H20: 0 | I20: 338.8
B21: 2020-0986 | C21: 44168 | D21: 2002 | E21: 338.8 | F21: 0 | G21: 0 | H21: 0 | I21: 338.8
B22: 2020-1128 | C22: 44196 | D22: 1974 | E22: 338.8 | F22: 0 | G22: 0 | H22: 0 | I22: 338.8
B23: 2021-0010 | C23: 44233 | D23: 1937 | E23: 338.8 | F23: 0 | G23: 0 | H23: 0 | I23: 338.8
B24: 2022-0553 | C24: 44765 | D24: 1405 | E24: 3025 | F24: 0 | G24: 0 | H24: 0 | I24: 3025
B25: R190024 | C25: 43497 | D25: 2673 | E25: 338.8 | F25: 0 | G25: 0 | H25: 0 | I25: 338.8
... B36: R190995 | C36: 43832 | D36: 2338 | E36: 338.8 | F36: 0 | G36: 0 | H36: 0 | I36: 338.8
A37: American Soulfood Total | E37: 11495 | F37: 0 | G37: 0 | H37: 0 | I37: 11495
A38: Amigo Top B.V. | B38: 102026-0538 | C38: 46140 | D38: 30 | E38: 5749.21 | F38: 5749.21 | G38: 0 | H38: 0 | I38: 0
B39: 2024-1136 | C39: 45579 | D39: 591 | E39: 5407.59 | F39: 0 | G39: 0 | H39: 0 | I39: 5407.59
A40: Amigo Top B.V. Total | E40: 11156.8 | F40: 5749.21 | G40: 0 | H40: 0 | I40: 5407.59
A41: Auroria Pecunia B.V. | B41: 102025-0740 | C41: 45869 | D41: 301 | E41: 653.4 | F41: 0 | G41: 0 | H41: 0 | I41: 653.4
B42: 102025-0984 | C42: 45966 | D42: 204 | E42: 653.4 | F42: 0 | G42: 0 | H42: 0 | I42: 653.4
B43: 102026-0007 | C43: 46060 | D43: 110 | E43: 653.4 | F43: 0 | G43: 0 | H43: 0 | I43: 653.4
B44: 102026-0364 | C44: 46134 | D44: 36 | E44: 707.85 | F44: 0 | G44: 707.85 | H44: 0 | I44: 0
B45: 102026-0442 | C45: 46148 | D45: 22 | E45: 653.4 | F45: 653.4 | G45: 0 | H45: 0 | I45: 0
B46: 2023-1142 | C46: 45267 | D46: 903 | E46: 217.8 | F46: 0 | G46: 0 | H46: 0 | I46: 217.8
B47: 2023-1239 | C47: 45295 | D47: 875 | E47: 217.8 | F47: 0 | G47: 0 | H47: 0 | I47: 217.8
B48: 2024-0049 | C48: 45325 | D48: 845 | E48: 217.8 | F48: 0 | G48: 0 | H48: 0 | I48: 217.8
B49: 2024-0132 | C49: 45357 | D49: 813 | E49: 217.8 | F49: 0 | G49: 0 | H49: 0 | I49: 217.8
B50: 2024-0258 | C50: 45387 | D50: 783 | E50: 217.8 | F50: 0 | G50: 0 | H50: 0 | I50: 217.8
B51: 2024-0386 | C51: 45416 | D51: 754 | E51: 217.8 | F51: 0 | G51: 0 | H51: 0 | I51: 217.8
B52: 2024-0488 | C52: 45448 | D52: 722 | E52: 217.8 | F52: 0 | G52: 0 | H52: 0 | I52: 217.8
B53: 2024-0583 | C53: 45476 | D53: 694 | E53: 217.8 | F53: 0 | G53: 0 | H53: 0 | I53: 217.8
... B64: 2025-0434 | C64: 45780 | D64: 390 | E64: 653.4 | F64: 0 | G64: 0 | H64: 0 | I64: 653.4
A65: Auroria Pecunia B.V. Total | E65: 7979.95 | F65: 653.4 | G65: 707.85 | H65: 0 | I65: 6618.7
A66: Autobedrijf Tinga & Zn | B66: 102025-0791 | C66: 45886 | D66: 284 | E66: 9075 | F66: 0 | G66: 0 | H66: 0 | I66: 9075
A67: Autobedrijf Tinga & Zn Total | E67: 9075 | F67: 0 | G67: 0 | H67: 0 | I67: 9075
A68: Autodemontagebedrijf Th. van Gils B.V. | B68: 102026-0365 | C68: 46134 | D68: 36 | E68: 9164.18 | F68: 0 | G68: 9164.18 | H68: 0 | I68: 0
B69: 102026-0419 | C69: 46143 | D69: 27 | E69: 2998.38 | F69: 2998.38 | G69: 0 | H69: 0 | I69: 0
A70: Autodemontagebedrijf Th. van Gils B.V. Total | E70: 12162.56 | F70: 2998.38 | G70: 9164.18 | H70: 0 | I70: 0
A71: B. Jeddi | B71: 2023-0884 | C71: 45183 | D71: 987 | E71: 187.76 | F71: 0 | G71: 0 | H71: 0 | I71: 187.76
B72: 2023-0885 | C72: 45183 | D72: 987 | E72: 2330.76 | F72: 0 | G72: 0 | H72: 0 | I72: 2330.76
A73: B. Jeddi Total | E73: 2518.52 | F73: 0 | G73: 0 | H73: 0 | I73: 2518.52
A74: Bats | B74: 2025-0154 | C74: 45705 | D74: 465 | E74: 363 | F74: 0 | G74: 0 | H74: 0 | I74: 363
A75: Bats Total | E75: 363 | F75: 0 | G75: 0 | H75: 0 | I75: 363
A76: Bense Bouw B.V. | B76: 2020-0010 | C76: 43879 | D76: 2291 | E76: 240.79 | F76: 0 | G76: 0 | H76: 0 | I76: 240.79
B77: 2020-0124 | C77: 43879 | D77: 2291 | E77: 240.79 | F77: 0 | G77: 0 | H77: 0 | I77: 240.79
B78: 2020-0272 | C78: 43913 | D78: 2257 | E78: 30.25 | F78: 0 | G78: 0 | H78: 0 | I78: 30.25
B79: 2020-0298 | C79: 43936 | D79: 2234 | E79: 30.25 | F79: 0 | G79: 0 | H79: 0 | I79: 30.25
B80: 2020-0429 | C80: 43963 | D80: 2207 | E80: 30.25 | F80: 0 | G80: 0 | H80: 0 | I80: 30.25
B81: 2020-1165 | C81: 44180 | D81: 1990 | E81: 30.25 | F81: 0 | G81: 0 | H81: 0 | I81: 30.25
B82: 2021-0313 | C82: 44271 | D82: 1899 | E82: 30.25 | F82: 0 | G82: 0 | H82: 0 | I82: 30.25
B83: R191127 | C83: 43860 | D83: 2310 | E83: 644.04 | F83: 0 | G83: 0 | H83: 0 | I83: 644.04
A84: Bense Bouw B.V. Total | E84: 1276.87 | F84: 0 | G84: 0 | H84: 0 | I84: 1276.87
A85: Bladi shop | B85: 2023-0627 | C85: 45096 | D85: 1074 | E85: 350.9 | F85: 0 | G85: 0 | H85: 0 | I85: 350.9
B86: 2023-0682 | C86: 45124 | D86: 1046 | E86: 350.9 | F86: 0 | G86: 0 | H86: 0 | I86: 350.9
B87: 2023-0791 | C87: 45152 | D87: 1018 | E87: 30.25 | F87: 0 | G87: 0 | H87: 0 | I87: 30.25
B88: 2023-0876 | C88: 45155 | D88: 1015 | E88: 24.2 | F88: 0 | G88: 0 | H88: 0 | I88: 24.2
A89: Bladi shop Total | E89: 756.25 | F89: 0 | G89: 0 | H89: 0 | I89: 756.25
A90: By Lauyaju | B90: 2020-0014 | C90: 43895 | D90: 2275 | E90: 180.29 | F90: 0 | G90: 0 | H90: 0 | I90: 180.29
B91: 2020-0137 | C91: 43895 | D91: 2275 | E91: 180.29 | F91: 0 | G91: 0 | H91: 0 | I91: 180.29
B92: 2020-0232 | C92: 43920 | D92: 2250 | E92: 180.29 | F92: 0 | G92: 0 | H92: 0 | I92: 180.29
B93: R180439 | C93: 43435 | D93: 2735 | E93: 180.29 | F93: 0 | G93: 0 | H93: 0 | I93: 180.29
B94: R180498 | C94: 43469 | D94: 2701 | E94: 180.29 | F94: 0 | G94: 0 | H94: 0 | I94: 180.29
B95: R190009 | C95: 43497 | D95: 2673 | E95: 180.29 | F95: 0 | G95: 0 | H95: 0 | I95: 180.29
B96: R190098 | C96: 43532 | D96: 2638 | E96: 180.29 | F96: 0 | G96: 0 | H96: 0 | I96: 180.29
B97: R190170 | C97: 43559 | D97: 2611 | E97: 180.29 | F97: 0 | G97: 0 | H97: 0 | I97: 180.29
B98: R190267 | C98: 43593 | D98: 2577 | E98: 180.29 | F98: 0 | G98: 0 | H98: 0 | I98: 180.29
B99: R190347 | C99: 43616 | D99: 2554 | E99: 180.29 | F99: 0 | G99: 0 | H99: 0 | I99: 180.29
B100: R190440 | C100: 43651 | D100: 2519 | E100: 180.29 | F100: 0 | G100: 0 | H100: 0 | I100: 180.29
B101: R190534 | C101: 43678 | D101: 2492 | E101: 180.29 | F101: 0 | G101: 0 | H101: 0 | I101: 180.29
B102: R190628 | C102: 43708 | D102: 2462 | E102: 180.29 | F102: 0 | G102: 0 | H102: 0 | I102: 180.29
... B106: R191032 | C106: 43832 | D106: 2338 | E106: 180.29 | F106: 0 | G106: 0 | H106: 0 | I106: 180.29
A107: By Lauyaju Total | E107: 3064.93 | F107: 0 | G107: 0 | H107: 0 | I107: 3064.93
A108: C. Gray | B108: 2022-0544 | C108: 44751 | D108: 1419 | E108: 261.66 | F108: 0 | G108: 0 | H108: 0 | I108: 261.66
A109: C. Gray Total | E109: 261.66 | F109: 0 | G109: 0 | H109: 0 | I109: 261.66
A110: Coffeeshop Dizzy Duck B.V. | C110: 45325 | D110: 845 | E110: -514.25 | F110: 0 | G110: 0 | H110: 0 | I110: -514.25
C111: 45366 | D111: 804 | E111: -514.25 | F111: 0 | G111: 0 | H111: 0 | I111: -514.25
A112: Coffeeshop Dizzy Duck B.V. Total | E112: -1028.5 | F112: 0 | G112: 0 | H112: 0 | I112: -1028.5
A113: Coöperatieve Vijftientien U.A. | B113: 102025-0578 | C113: 45819 | D113: 351 | E113: 4962.01 | F113: 0 | G113: 0 | H113: 0 | I113: 4962.01
A114: Coöperatieve Vijftientien U.A. Total | E114: 4962.01 | F114: 0 | G114: 0 | H114: 0 | I114: 4962.01
A115: Deel 2 | B115: R190107 | C115: 43532 | D115: 2638 | E115: 338.8 | F115: 0 | G115: 0 | H115: 0 | I115: 338.8
A116: Deel 2 Total | E116: 338.8 | F116: 0 | G116: 0 | H116: 0 | I116: 338.8
A117: Deelman Holding B.V. | B117: 102025-0525 | C117: 45812 | D117: 358 | E117: 242 | F117: 0 | G117: 0 | H117: 0 | I117: 242
B118: 102025-0606 | C118: 45840 | D118: 330 | E118: 242 | F118: 0 | G118: 0 | H118: 0 | I118: 242
B119: 102025-0708 | C119: 45869 | D119: 301 | E119: 242 | F119: 0 | G119: 0 | H119: 0 | I119: 242
B120: 102025-0811 | C120: 45903 | D120: 267 | E120: 242 | F120: 0 | G120: 0 | H120: 0 | I120: 242
B121: 102025-0898 | C121: 45931 | D121: 239 | E121: 242 | F121: 0 | G121: 0 | H121: 0 | I121: 242
B122: 102025-0990 | C122: 45966 | D122: 204 | E122: 242 | F122: 0 | G122: 0 | H122: 0 | I122: 242
B123: 102025-1122 | C123: 45996 | D123: 174 | E123: 242 | F123: 0 | G123: 0 | H123: 0 | I123: 242
...

Sheet Top20 
A1: Last update: | B1: 46170
A2: High Priority Customers
B3: =SUBTOTAL(9,B5:B124) -> 4381621.8 | C3: =Ouderdomsanalyseperdebiteur!J1075-'Top20 '!B3 -> 1.2107193e-08
A4: NaamDebiteur | B4: Total outstanding balance | C4: Oldest invoice | D4: Days outstanding | E4: Last contact date | F4: Reason not paid (if known) | G4: Owner (finance / account manager) | H4: Remarks | I4: Action Item | K4: Call date | L4: Commitment | M4: Amount | N4: Follow-up Date
A5: JPA Van Noort Gassler & Co B.V. | B5: =SUMIFS(Ouderdomsanalyseperdebiteur!J:J,Ouderdomsanalyseperdebiteur!D:D,'Top20 '!A:A) -> 3729562.3 | C5: 45448 | D5: =TODAY()-C5 -> 722 | I5: JPA
A6: Van Noort Gassler & Co. 's-Gravenhage B.V. | B6: =SUMIFS(Ouderdomsanalyseperdebiteur!J:J,Ouderdomsanalyseperdebiteur!D:D,'Top20 '!A:A) -> 203002.73 | C6: 43690 | D6: =TODAY()-C6 -> 2480 | I6: VNG
A7: Van Noort Gassler & Co. Utrecht B.V. | B7: =SUMIFS(Ouderdomsanalyseperdebiteur!J:J,Ouderdomsanalyseperdebiteur!D:D,'Top20 '!A:A) -> 0 | C7: 46076 | D7: =TODAY()-C7 -> 94 | I7: VNG
A8: Van Noort Gassler & Co. Haarlem B.V. | B8: =SUMIFS(Ouderdomsanalyseperdebiteur!J:J,Ouderdomsanalyseperdebiteur!D:D,'Top20 '!A:A) -> 18214.83 | C8: 44943 | D8: =TODAY()-C8 -> 1227 | I8: VNG
A9: Pijnex Internationationaal Transport | B9: =SUMIFS(Ouderdomsanalyseperdebiteur!J:J,Ouderdomsanalyseperdebiteur!D:D,'Top20 '!A:A) -> 44425 | C9: 45684 | D9: =TODAY()-C9 -> 486 | G9: Quirin Nieuwenhuizen | I9: Payment agreement set-up - we need to update the monthly payment from 1k to 3k
A10: R.A.U. Juchter van Bergen Quast B.V. | B10: =SUMIFS(Ouderdomsanalyseperdebiteur!J:J,Ouderdomsanalyseperdebiteur!D:D,'Top20 '!A:A) -> 40270.76 | C10: 43098 | D10: =TODAY()-C10 -> 3072 | G10: Laurens Nijssen | H10: No action needed
A11: LUKOIL International Upstream Holdings B.V. | B11: =SUMIFS(Ouderdomsanalyseperdebiteur!J:J,Ouderdomsanalyseperdebiteur!D:D,'Top20 '!A:A) -> 28645.24 | C11: 46009 | D11: =TODAY()-C11 -> 161 | G11: Shaira Castillo-Vierneza | I11: to check if payment is updated
A12: Vincent van der Weijden Holding B.V. | B12: =SUMIFS(Ouderdomsanalyseperdebiteur!J:J,Ouderdomsanalyseperdebiteur!D:D,'Top20 '!A:A) -> 23347.62 | C12: 44412 | D12: =TODAY()-C12 -> 1758 | G12: Quirin Nieuwenhuizen | H12: Payment agreement set up | I12: to check if payment is updated
A13: Lewis Fashion Group B.V. | B13: =SUMIFS(Ouderdomsanalyseperdebiteur!J:J,Ouderdomsanalyseperdebiteur!D:D,'Top20 '!A:A) -> 23075.47 | C13: 45450 | D13: =TODAY()-C13 -> 720 | G13: Quirin Nieuwenhuizen | H13: Payment agreement set up | I13: to check if payment is updated
A14: Stichting Studeren/Werken op Maat | B14: =SUMIFS(Ouderdomsanalyseperdebiteur!J:J,Ouderdomsanalyseperdebiteur!D:D,'Top20 '!A:A) -> 20189.76 | C14: 45699 | D14: =TODAY()-C14 -> 471 | G14: Betty Kieboom | I14: Email - Nice email
A15: Duckies B.V. | B15: =SUMIFS(Ouderdomsanalyseperdebiteur!J:J,Ouderdomsanalyseperdebiteur!D:D,'Top20 '!A:A) -> 18595.52 | C15: 45726 | D15: =TODAY()-C15 -> 444 | G15: Quirin Nieuwenhuizen | I15: Email - Nice email
A16: Elstgeest Ventures B.V. | B16: =SUMIFS(Ouderdomsanalyseperdebiteur!J:J,Ouderdomsanalyseperdebiteur!D:D,'Top20 '!A:A) -> 12552.48 | C16: 45691 | D16: =TODAY()-C16 -> 479 | G16: Quirin Nieuwenhuizen | I16: Email - Strickt email
A17: Autodemontagebedrijf Th. van Gils B.V. | B17: =SUMIFS(Ouderdomsanalyseperdebiteur!J:J,Ouderdomsanalyseperdebiteur!D:D,'Top20 '!A:A) -> 12162.56 | C17: 46104 | D17: =TODAY()-C17 -> 66 | G17: Betty Kieboom | I17: Email - Standard
A18: Rijks Investments B.V. | B18: =SUMIFS(Ouderdomsanalyseperdebiteur!J:J,Ouderdomsanalyseperdebiteur!D:D,'Top20 '!A:A) -> 12014.16 | C18: 44378 | D18: =TODAY()-C18 -> 1792 | G18: Edwin Mafficioli del Castelletto | I18: Deurwaarder
A19: G8plus B.V. | B19: =SUMIFS(Ouderdomsanalyseperdebiteur!J:J,Ouderdomsanalyseperdebiteur!D:D,'Top20 '!A:A) -> 11753.15 | C19: 42768 | D19: =TODAY()-C19 -> 3402 | G19: Laurens Nijssen | I19: Deurwaarder
A20: American Soulfood | B20: =SUMIFS(Ouderdomsanalyseperdebiteur!J:J,Ouderdomsanalyseperdebiteur!D:D,'Top20 '!A:A) -> 11495 | C20: 43467 | D20: =TODAY()-C20 -> 2703 | G20: Betty Kieboom | I20: Deurwaarder BE - navragen
A21: Serviceheroes B.V. | B21: =SUMIFS(Ouderdomsanalyseperdebiteur!J:J,Ouderdomsanalyseperdebiteur!D:D,'Top20 '!A:A) -> 11187.06 | C21: 45726 | D21: =TODAY()-C21 -> 444 | G21: Edwin Mafficioli del Castelletto | I21: Email - Standard
A22: Amigo Top B.V. | B22: =SUMIFS(Ouderdomsanalyseperdebiteur!J:J,Ouderdomsanalyseperdebiteur!D:D,'Top20 '!A:A) -> 11156.8 | C22: 45565 | D22: =TODAY()-C22 -> 605 | G22: Edwin Mafficioli del Castelletto | H22: No action needed; No reminder needed.
A23: TOFF concept | B23: =SUMIFS(Ouderdomsanalyseperdebiteur!J:J,Ouderdomsanalyseperdebiteur!D:D,'Top20 '!A:A) -> 9764.14 | C23: 44927 | D23: =TODAY()-C23 -> 1243 | G23: Quirin Nieuwenhuizen | I23: Payment Agreement
A24: Autobedrijf Tinga & Zn | B24: =SUMIFS(Ouderdomsanalyseperdebiteur!J:J,Ouderdomsanalyseperdebiteur!D:D,'Top20 '!A:A) -> 9075 | C24: 45856 | D24: =TODAY()-C24 -> 314 | G24: Edwin Mafficioli del Castelletto | I24: Email - Standard
A25: Hans van Rooij Consultancy | B25: =SUMIFS(Ouderdomsanalyseperdebiteur!J:J,Ouderdomsanalyseperdebiteur!D:D,'Top20 '!A:A) -> 9075 | C25: 44537 | D25: =TODAY()-C25 -> 1633 | G25: Laura Vet-van Waart | I25: To Edwin
A26: Heron Groep B.V. | B26: =SUMIFS(Ouderdomsanalyseperdebiteur!J:J,Ouderdomsanalyseperdebiteur!D:D,'Top20 '!A:A) -> 8205.38 | C26: 45672 | D26: =TODAY()-C26 -> 498 | G26: Betty Kieboom | I26: Email - Standard
A27: Auroria Pecunia B.V. | B27: =SUMIFS(Ouderdomsanalyseperdebiteur!J:J,Ouderdomsanalyseperdebiteur!D:D,'Top20 '!A:A) -> 7979.95 | C27: 45237 | D27: =TODAY()-C27 -> 933 | G27: Quirin Nieuwenhuizen | I27: Email - Nice email
A28: M.P. Polderdijk Holding B.V. | B28: =SUMIFS(Ouderdomsanalyseperdebiteur!J:J,Ouderdomsanalyseperdebiteur!D:D,'Top20 '!A:A) -> 6322.25 | C28: 43467 | D28: =TODAY()-C28 -> 2703 | G28: Betty Kieboom | I28: Deurwaarder BE - navragen
A29: Interlex | B29: =SUMIFS(Ouderdomsanalyseperdebiteur!J:J,Ouderdomsanalyseperdebiteur!D:D,'Top20 '!A:A) -> 5915.51 | C29: 43846 | D29: =TODAY()-C29 -> 2324 | G29: Edwin Mafficioli del Castelletto
A30: Levels Diagnostics B.V. | B30: =SUMIFS(Ouderdomsanalyseperdebiteur!J:J,Ouderdomsanalyseperdebiteur!D:D,'Top20 '!A:A) -> 5747.5 | C30: 46125 | D30: =TODAY()-C30 -> 45 | G30: Edwin Mafficioli del Castelletto | I30: Email - Nice email
A31: Coöperatieve Vijftientien U.A. | B31: =SUMIFS(Ouderdomsanalyseperdebiteur!J:J,Ouderdomsanalyseperdebiteur!D:D,'Top20 '!A:A) -> 4962.01 | C31: 45789 | D31: =TODAY()-C31 -> 381 | G31: Edwin Mafficioli del Castelletto
A32: Deelman Timmerwerken B.V. | B32: =SUMIFS(Ouderdomsanalyseperdebiteur!J:J,Ouderdomsanalyseperdebiteur!D:D,'Top20 '!A:A) -> 4900.5 | C32: 45782 | D32: =TODAY()-C32 -> 388 | G32: Quirin Nieuwenhuizen | I32: Email - Nice email
A33: AirFlow Luchtkanalen B.V. | B33: =SUMIFS(Ouderdomsanalyseperdebiteur!J:J,Ouderdomsanalyseperdebiteur!D:D,'Top20 '!A:A) -> 4779.88 | C33: 45355 | D33: =TODAY()-C33 -> 815 | G33: Quirin Nieuwenhuizen | I33: Email - Nice email
A34: Meydanim Den Haag B.V. | B34: =SUMIFS(Ouderdomsanalyseperdebiteur!J:J,Ouderdomsanalyseperdebiteur!D:D,'Top20 '!A:A) -> 4737.58 | C34: 43774 | D34: =TODAY()-C34 -> 2396 | G34: Betty Kieboom | I34: Deurwaarder
A35: Ray Consultancy B.V. | B35: =SUMIFS(Ouderdomsanalyseperdebiteur!J:J,Ouderdomsanalyseperdebiteur!D:D,'Top20 '!A:A) -> 4640.37 | C35: 43679 | D35: =TODAY()-C35 -> 2491 | G35: Laurens Nijssen | I35: Deurwaarder
A36: Stichting Zwitserse Kamer van Koophandel in Nederland | B36: =SUMIFS(Ouderdomsanalyseperdebiteur!J:J,Ouderdomsanalyseperdebiteur!D:D,'Top20 '!A:A) -> 4537.5 | C36: 44886 | D36: =TODAY()-C36 -> 1284 | G36: Laura Vet-van Waart
A37: RMA Loodgieter | B37: =SUMIFS(Ouderdomsanalyseperdebiteur!J:J,Ouderdomsanalyseperdebiteur!D:D,'Top20 '!A:A) -> 3682.64 | C37: 45481 | D37: =TODAY()-C37 -> 689 | G37: Quirin Nieuwenhuizen | I37: Deurwaarder
A38: A.J.F. Jansen B.V. | B38: =SUMIFS(Ouderdomsanalyseperdebiteur!J:J,Ouderdomsanalyseperdebiteur!D:D,'Top20 '!A:A) -> 3646.64 | C38: 45712 | D38: =TODAY()-C38 -> 458 | G38: Betty Kieboom | I38: Email - Nice email
A39: Respublica B.V. | B39: =SUMIFS(Ouderdomsanalyseperdebiteur!J:J,Ouderdomsanalyseperdebiteur!D:D,'Top20 '!A:A) -> 3584.63 | C39: 45957 | D39: =TODAY()-C39 -> 213 | G39: Edwin Mafficioli del Castelletto | I39: to deurwaarder
A40: RJD Infra | B40: =SUMIFS(Ouderdomsanalyseperdebiteur!J:J,Ouderdomsanalyseperdebiteur!D:D,'Top20 '!A:A) -> 3575.55 | C40: 45048 | D40: =TODAY()-C40 -> 1122 | G40: Nowshin Jahan | I40: Deurwaarder
A41: Moussaten Infra | B41: =SUMIFS(Ouderdomsanalyseperdebiteur!J:J,Ouderdomsanalyseperdebiteur!D:D,'Top20 '!A:A) -> 3521.1 | C41: 43678 | D41: =TODAY()-C41 -> 2492 | G41: Betty Kieboom
A42: Plaats22 | B42: =SUMIFS(Ouderdomsanalyseperdebiteur!J:J,Ouderdomsanalyseperdebiteur!D:D,'Top20 '!A:A) -> 3444.77 | C42: 46133 | D42: =TODAY()-C42 -> 37 | G42: Quirin Nieuwenhuizen
A43: Rob Hotting Art & Concept | B43: =SUMIFS(Ouderdomsanalyseperdebiteur!J:J,Ouderdomsanalyseperdebiteur!D:D,'Top20 '!A:A) -> 3251.27 | C43: 45048 | D43: =TODAY()-C43 -> 1122 | G43: Quirin Nieuwenhuizen
A44: MBE Invest B.V. | B44: =SUMIFS(Ouderdomsanalyseperdebiteur!J:J,Ouderdomsanalyseperdebiteur!D:D,'Top20 '!A:A) -> 3194.4 | C44: 45993 | D44: =TODAY()-C44 -> 177 | G44: Quirin Nieuwenhuizen
A45: Yepmedia B.V. | B45: =SUMIFS(Ouderdomsanalyseperdebiteur!J:J,Ouderdomsanalyseperdebiteur!D:D,'Top20 '!A:A) -> 3156.59 | C45: 45600 | D45: =TODAY()-C45 -> 570 | G45: Quirin Nieuwenhuizen
A46: Grefet Limited | B46: =SUMIFS(Ouderdomsanalyseperdebiteur!J:J,Ouderdomsanalyseperdebiteur!D:D,'Top20 '!A:A) -> 3138.43 | C46: 45411 | D46: =TODAY()-C46 -> 759 | G46: Laura Vet-van Waart
A47: By Lauyaju | B47: =SUMIFS(Ouderdomsanalyseperdebiteur!J:J,Ouderdomsanalyseperdebiteur!D:D,'Top20 '!A:A) -> 3064.93 | C47: 43405 | D47: =TODAY()-C47 -> 2765 | G47: Betty Kieboom | I47: Deurwaarder
A48: Z & S Sales and Marketing B.V. | B48: =SUMIFS(Ouderdomsanalyseperdebiteur!J:J,Ouderdomsanalyseperdebiteur!D:D,'Top20 '!A:A) -> 2571.33 | C48: 42948 | D48: =TODAY()-C48 -> 3222 | G48: for checking | I48: Deurwaarder
A49: B. Jeddi | B49: =SUMIFS(Ouderdomsanalyseperdebiteur!J:J,Ouderdomsanalyseperdebiteur!D:D,'Top20 '!A:A) -> 2518.52 | C49: 45153 | D49: =TODAY()-C49 -> 1017 | G49: for checking | I49: Deurwaarder
A50: Korswill NL | B50: =SUMIFS(Ouderdomsanalyseperdebiteur!J:J,Ouderdomsanalyseperdebiteur!D:D,'Top20 '!A:A) -> 2450.25 | C50: 45873 | D50: =TODAY()-C50 -> 297 | G50: Quirin Nieuwenhuizen
A51: M.P. Harten | B51: =SUMIFS(Ouderdomsanalyseperdebiteur!J:J,Ouderdomsanalyseperdebiteur!D:D,'Top20 '!A:A) -> 2402.94 | C51: 45726 | D51: =TODAY()-C51 -> 444 | G51: Edwin Mafficioli del Castelletto
A52: Mavi infra | B52: =SUMIFS(Ouderdomsanalyseperdebiteur!J:J,Ouderdomsanalyseperdebiteur!D:D,'Top20 '!A:A) -> 2263.91 | C52: 43621 | D52: =TODAY()-C52 -> 2549 | G52: Betty Kieboom | I52: Deurwaarder
A53: Deelman Holding B.V. | B53: =SUMIFS(Ouderdomsanalyseperdebiteur!J:J,Ouderdomsanalyseperdebiteur!D:D,'Top20 '!A:A) -> 3935.53 | C53: 45782 | D53: =TODAY()-C53 -> 388 | G53: Quirin Nieuwenhuizen
A54: Eye Tech International B.V. | B54: =SUMIFS(Ouderdomsanalyseperdebiteur!J:J,Ouderdomsanalyseperdebiteur!D:D,'Top20 '!A:A) -> 2128.11 | C54: 43440 | D54: =TODAY()-C54 -> 2730 | G54: for checking | I54: Deurwaarder
A55: M.O. Multiservice | B55: =SUMIFS(Ouderdomsanalyseperdebiteur!J:J,Ouderdomsanalyseperdebiteur!D:D,'Top20 '!A:A) -> 2078.43 | C55: 43774 | D55: =TODAY()-C55 -> 2396 | G55: Betty Kieboom | I55: To deurwaarder
A56: Van Bergen 1795 B.V. | B56: =SUMIFS(Ouderdomsanalyseperdebiteur!J:J,Ouderdomsanalyseperdebiteur!D:D,'Top20 '!A:A) -> 1969.88 | C56: 46030 | D56: =TODAY()-C56 -> 140 | G56: Edwin Mafficioli del Castelletto
A57: Rick Sandee Riooltechniek | B57: =SUMIFS(Ouderdomsanalyseperdebiteur!J:J,Ouderdomsanalyseperdebiteur!D:D,'Top20 '!A:A) -> 1887.6 | C57: 45726 | D57: =TODAY()-C57 -> 444 | G57: Quirin Nieuwenhuizen
A58: Stichting Antarctica Foundation | B58: =SUMIFS(Ouderdomsanalyseperdebiteur!J:J,Ouderdomsanalyseperdebiteur!D:D,'Top20 '!A:A) -> 1815 | C58: 45047 | D58: =TODAY()-C58 -> 1123 | G58: Edwin Mafficioli del Castelletto
A59: Kraskino Consultants Ltd. | B59: =SUMIFS(Ouderdomsanalyseperdebiteur!J:J,Ouderdomsanalyseperdebiteur!D:D,'Top20 '!A:A) -> 1725.26 | C59: 44796 | D59: =TODAY()-C59 -> 1374 | G59: Betty Kieboom
A60: DreamersInc | B60: =SUMIFS(Ouderdomsanalyseperdebiteur!J:J,Ouderdomsanalyseperdebiteur!D:D,'Top20 '!A:A) -> 1724.25 | C60: 45779 | D60: =TODAY()-C60 -> 391 | G60: Edwin Mafficioli del Castelletto
A61: Year 2024 | B61: =SUMIFS(Ouderdomsanalyseperdebiteur!J:J,Ouderdomsanalyseperdebiteur!D:D,'Top20 '!A:A) -> 1627.45 | C61: 45628 | D61: =TODAY()-C61 -> 542 | G61: Quirin Nieuwenhuizen | I61: Deurwaarder
A62: Hooimani El M'Barki Real Estate B.V. | B62: =SUMIFS(Ouderdomsanalyseperdebiteur!J:J,Ouderdomsanalyseperdebiteur!D:D,'Top20 '!A:A) -> 1615.35 | C62: 45966 | D62: =TODAY()-C62 -> 204 | G62: Quirin Nieuwenhuizen
A63: FTOU B.V. | B63: =SUMIFS(Ouderdomsanalyseperdebiteur!J:J,Ouderdomsanalyseperdebiteur!D:D,'Top20 '!A:A) -> 1599.01 | C63: 44110 | D63: =TODAY()-C63 -> 2060 | G63: Betty Kieboom | I63: Deurwaarder
A64: Zorlu Infra | B64: =SUMIFS(Ouderdomsanalyseperdebiteur!J:J,Ouderdomsanalyseperdebiteur!D:D,'Top20 '!A:A) -> 1544.43 | C64: 43865 | D64: =TODAY()-C64 -> 2305 | G64: Betty Kieboom | I64: Deurwaarder
A65: Willems WorkShop | B65: =SUMIFS(Ouderdomsanalyseperdebiteur!J:J,Ouderdomsanalyseperdebiteur!D:D,'Top20 '!A:A) -> 1474.71 | C65: 43221 | D65: =TODAY()-C65 -> 2949 | G65: for checking
A66: Rijks Invest B.V. | B66: =SUMIFS(Ouderdomsanalyseperdebiteur!J:J,Ouderdomsanalyseperdebiteur!D:D,'Top20 '!A:A) -> 1452 | C66: 45033 | D66: =TODAY()-C66 -> 1137 | G66: Edwin Mafficioli del Castelletto | I66: Deurwaarder
A67: Lelie Engineering | B67: =SUMIFS(Ouderdomsanalyseperdebiteur!J:J,Ouderdomsanalyseperdebiteur!D:D,'Top20 '!A:A) -> 1403.6 | C67: 46030 | D67: =TODAY()-C67 -> 140 | G67: Quirin Nieuwenhuizen
A68: Bense Bouw B.V. | B68: =SUMIFS(Ouderdomsanalyseperdebiteur!J:J,Ouderdomsanalyseperdebiteur!D:D,'Top20 '!A:A) -> 1276.87 | C68: 43830 | D68: =TODAY()-C68 -> 2340 | G68: Betty Kieboom
A69: Manfred Spaargaren Confiserie | B69: =SUMIFS(Ouderdomsanalyseperdebiteur!J:J,Ouderdomsanalyseperdebiteur!D:D,'Top20 '!A:A) -> 1210 | C69: 43042 | D69: =TODAY()-C69 -> 3128 | G69: for checking
A70: Happy B.V. | B70: =SUMIFS(Ouderdomsanalyseperdebiteur!J:J,Ouderdomsanalyseperdebiteur!D:D,'Top20 '!A:A) -> 1210 | C70: 45726 | D70: =TODAY()-C70 -> 444 | G70: Laura Vet-van Waart
A71: Van Gils Onroerend Goed B.V. | B71: =SUMIFS(Ouderdomsanalyseperdebiteur!J:J,Ouderdomsanalyseperdebiteur!D:D,'Top20 '!A:A) -> 1151.92 | C71: 46030 | D71: =TODAY()-C71 -> 140 | G71: Betty Kieboom
A72: Stichting Werken Op Maat. | B72: =SUMIFS(Ouderdomsanalyseperdebiteur!J:J,Ouderdomsanalyseperdebiteur!D:D,'Top20 '!A:A) -> 1084.16 | C72: 46031 | D72: =TODAY()-C72 -> 139 | G72: Laura Vet-van Waart
A73: Zentrex Capital B.V. | B73: =SUMIFS(Ouderdomsanalyseperdebiteur!J:J,Ouderdomsanalyseperdebiteur!D:D,'Top20 '!A:A) -> 1070.85 | C73: 46055 | D73: =TODAY()-C73 -> 115 | G73: Edwin Mafficioli del Castelletto
A74: Meat & Chicken Forepark B.V. | B74: =SUMIFS(Ouderdomsanalyseperdebiteur!J:J,Ouderdomsanalyseperdebiteur!D:D,'Top20 '!A:A) -> 1017.91 | C74: 43951 | D74: =TODAY()-C74 -> 2219 | G74: Edwin Mafficioli del Castelletto | I74: Deurwaarder
A75: VOF T.H. Thio en T.H. Thio-Ong | B75: =SUMIFS(Ouderdomsanalyseperdebiteur!J:J,Ouderdomsanalyseperdebiteur!D:D,'Top20 '!A:A) -> 998.25 | C75: 46094 | D75: =TODAY()-C75 -> 76 | G75: Betty Kieboom
A76: FCKLCK.STUDIO B.V. | B76: =SUMIFS(Ouderdomsanalyseperdebiteur!J:J,Ouderdomsanalyseperdebiteur!D:D,'Top20 '!A:A) -> 907.5 | C76: 46030 | D76: =TODAY()-C76 -> 140 | G76: Quirin Nieuwenhuizen
A77: Hashtag Holding B.V. | B77: =SUMIFS(Ouderdomsanalyseperdebiteur!J:J,Ouderdomsanalyseperdebiteur!D:D,'Top20 '!A:A) -> 895.4 | C77: 43818 | D77: =TODAY()-C77 -> 2352 | G77: Laura Vet-van Waart
A78: Payslip Ltd. | B78: =SUMIFS(Ouderdomsanalyseperdebiteur!J:J,Ouderdomsanalyseperdebiteur!D:D,'Top20 '!A:A) -> 848.52 | C78: 44249 | D78: =TODAY()-C78 -> 1921 | G78: Edwin Mafficioli del Castelletto
A79: TelePlusGSM Retail B.V. | B79: =SUMIFS(Ouderdomsanalyseperdebiteur!J:J,Ouderdomsanalyseperdebiteur!D:D,'Top20 '!A:A) -> 830.06 | C79: 43949 | D79: =TODAY()-C79 -> 2221 | G79: Betty Kieboom | I79: Deurwaarder
A80: Zengin Oglanlar Holding B.V. | B80: =SUMIFS(Ouderdomsanalyseperdebiteur!J:J,Ouderdomsanalyseperdebiteur!D:D,'Top20 '!A:A) -> 757.6 | C80: 43865 | D80: =TODAY()-C80 -> 2305 | G80: Betty Kieboom | I80: Deurwaarder
A81: Bladi shop | B81: =SUMIFS(Ouderdomsanalyseperdebiteur!J:J,Ouderdomsanalyseperdebiteur!D:D,'Top20 '!A:A) -> 756.25 | C81: 45082 | D81: =TODAY()-C81 -> 1088 | G81: Betty Kieboom | I81: Deurwaarder
A82: Gaoui Beheer B.V. | B82: =SUMIFS(Ouderdomsanalyseperdebiteur!J:J,Ouderdomsanalyseperdebiteur!D:D,'Top20 '!A:A) -> 726 | C82: 44109 | D82: =TODAY()-C82 -> 2061 | G82: Betty Kieboom | I82: Deurwaarder
A83: Van Gils Holding B.V. | B83: =SUMIFS(Ouderdomsanalyseperdebiteur!J:J,Ouderdomsanalyseperdebiteur!D:D,'Top20 '!A:A) -> 715.11 | C83: 46118 | D83: =TODAY()-C83 -> 52 | G83: Betty Kieboom
A84: Korput Consultancy B.V. | B84: =SUMIFS(Ouderdomsanalyseperdebiteur!J:J,Ouderdomsanalyseperdebiteur!D:D,'Top20 '!A:A) -> 574.75 | C84: 46118 | D84: =TODAY()-C84 -> 52 | G84: Quirin Nieuwenhuizen
A85: Patrick van Gils Beheer B.V. | B85: =SUMIFS(Ouderdomsanalyseperdebiteur!J:J,Ouderdomsanalyseperdebiteur!D:D,'Top20 '!A:A) -> 563.86 | C85: 46118 | D85: =TODAY()-C85 -> 52 | G85: Betty Kieboom
A86: Vindure B.V. | B86: =SUMIFS(Ouderdomsanalyseperdebiteur!J:J,Ouderdomsanalyseperdebiteur!D:D,'Top20 '!A:A) -> 0 | C86: 46119 | D86: =TODAY()-C86 -> 51 | G86: Laura Vet-van Waart
A87: Paragon 28 Medical Devices Trading Limited | B87: =SUMIFS(Ouderdomsanalyseperdebiteur!J:J,Ouderdomsanalyseperdebiteur!D:D,'Top20 '!A:A) -> 527 | C87: 44573 | D87: =TODAY()-C87 -> 1597 | G87: Laura Vet-van Waart
A88: Kipcentrum Forepark B.V. | B88: =SUMIFS(Ouderdomsanalyseperdebiteur!J:J,Ouderdomsanalyseperdebiteur!D:D,'Top20 '!A:A) -> 517.28 | C88: 44840 | D88: =TODAY()-C88 -> 1330 | G88: Edwin Mafficioli del Castelletto
A89: Tradeplus24 Nederland B.V. | B89: =SUMIFS(Ouderdomsanalyseperdebiteur!J:J,Ouderdomsanalyseperdebiteur!D:D,'Top20 '!A:A) -> 484 | C89: 46062 | D89: =TODAY()-C89 -> 108 | G89: Edwin Mafficioli del Castelletto
A90: Einhaus Holding B.V. | B90: =SUMIFS(Ouderdomsanalyseperdebiteur!J:J,Ouderdomsanalyseperdebiteur!D:D,'Top20 '!A:A) -> 484 | C90: 45936 | D90: =TODAY()-C90 -> 234 | G90: Quirin Nieuwenhuizen
A91: NL Working Capital B.V. | B91: =SUMIFS(Ouderdomsanalyseperdebiteur!J:J,Ouderdomsanalyseperdebiteur!D:D,'Top20 '!A:A) -> 484 | C91: 46062 | D91: =TODAY()-C91 -> 108 | G91: Edwin Mafficioli del Castelletto
A92: Valet Parkeer Service | B92: =SUMIFS(Ouderdomsanalyseperdebiteur!J:J,Ouderdomsanalyseperdebiteur!D:D,'Top20 '!A:A) -> 453.75 | C92: 45012 | D92: =TODAY()-C92 -> 1158 | G92: Laura Vet-van Waart | I92: Deurwaarder
A93: Looqa B.V. | B93: =SUMIFS(Ouderdomsanalyseperdebiteur!J:J,Ouderdomsanalyseperdebiteur!D:D,'Top20 '!A:A) -> 445.65 | C93: 45993 | D93: =TODAY()-C93 -> 177 | G93: Quirin Nieuwenhuizen
A94: Knowdis B.V. | B94: =SUMIFS(Ouderdomsanalyseperdebiteur!J:J,Ouderdomsanalyseperdebiteur!D:D,'Top20 '!A:A) -> 415.94 | C94: 46030 | D94: =TODAY()-C94 -> 140 | G94: Quirin Nieuwenhuizen
A95: Bats | B95: =SUMIFS(Ouderdomsanalyseperdebiteur!J:J,Ouderdomsanalyseperdebiteur!D:D,'Top20 '!A:A) -> 363 | C95: 45691 | D95: =TODAY()-C95 -> 479 | G95: Quirin Nieuwenhuizen
A96: New Learning Factory B.V. | B96: =SUMIFS(Ouderdomsanalyseperdebiteur!J:J,Ouderdomsanalyseperdebiteur!D:D,'Top20 '!A:A) -> 363 | C96: 45936 | D96: =TODAY()-C96 -> 234 | G96: Quirin Nieuwenhuizen
A97: NEVE Trans B.V. | B97: =SUMIFS(Ouderdomsanalyseperdebiteur!J:J,Ouderdomsanalyseperdebiteur!D:D,'Top20 '!A:A) -> 361.77 | C97: 45951 | D97: =TODAY()-C97 -> 219 | G97: Dave Nahar
A98: Morpho Holding B.V. | B98: =SUMIFS(Ouderdomsanalyseperdebiteur!J:J,Ouderdomsanalyseperdebiteur!D:D,'Top20 '!A:A) -> 356.95 | C98: 46118 | D98: =TODAY()-C98 -> 52 | G98: Laura Vet-van Waart
A99: Morpho AGRI I B.V. | B99: =SUMIFS(Ouderdomsanalyseperdebiteur!J:J,Ouderdomsanalyseperdebiteur!D:D,'Top20 '!A:A) -> 356.95 | C99: 46118 | D99: =TODAY()-C99 -> 52 | G99: Laura Vet-van Waart
A100: Deel 2 | B100: =SUMIFS(Ouderdomsanalyseperdebiteur!J:J,Ouderdomsanalyseperdebiteur!D:D,'Top20 '!A:A) -> 338.8 | C100: 43502 | D100: =TODAY()-C100 -> 2668 | G100: for checking | I100: Deurwaarder
...

Sheet Action item Summary
B1: Row Labels | C1: Count of NaamDebiteur | D1: Sum of Total outstanding balance | F1: Sum of Total outstanding balance
B2: Deurwaarder | C2: 24 | D2: 59985.01 | F2: Owner (finance / account manager) | G2: Action Item | H2: Total
B3: Grand Total | C3: 24 | D3: 59985.01 | F3: Betty Kieboom | G3: Deurwaarder | H3: 16279.77
G4: Deurwaarder BE - navragen | H4: 17817.25
G5: Email - Nice email | H5: 23836.4
G6: Email - Standard | H6: 20367.94
G7: to deurwaarder | H7: 2078.43
G8: (blank) | H8: 10236.72
F9: Betty Kieboom Total | H9: 90616.51
F10: Dave Nahar | G10: (blank) | H10: 361.77
F11: Dave Nahar Total | H11: 361.77
F12: Edwin Mafficioli del Castelletto | G12: Deurwaarder | H12: 14484.07
G13: Email - Nice email | H13: 5747.5
G14: Email - Standard | H14: 20262.06
G15: to deurwaarder | H15: 3584.63
G16: (blank) | H16: 31665.17
F17: Edwin Mafficioli del Castelletto Total | H17: 75743.43
F18: for checking | G18: Deurwaarder | H18: 3306.76
G19: (blank) | H19: 3265.81
F20: for checking Total | H20: 6572.57
F21: Laura Vet-van Waart | G21: Deurwaarder | H21: 453.75
G22: To Edwin | H22: 9075
G23: (blank) | H23: 12560.14
F24: Laura Vet-van Waart Total | H24: 22088.89
F25: Laurens Nijssen | G25: Deurwaarder | H25: 16575.02
G26: (blank) | H26: 40270.76
F27: Laurens Nijssen Total | H27: 56845.78
F28: Marcel Meerman | G28: (blank) | H28: -36905
F29: Marcel Meerman Total | H29: -36905
F30: Nowshin Jahan | G30: Deurwaarder | H30: 3575.55
F31: Nowshin Jahan Total | H31: 3575.55
F32: Quirin Nieuwenhuizen | G32: Deurwaarder | H32: 5310.09
G33: Email - Nice email | H33: 36255.85
G34: Email - Strickt email | H34: 12552.48
G35: Payment Agreement | H35: 9764.14
G36: Payment agreement set-up - we need to update the monthly payment from 1k to 3k | H36: 44425
G37: to check if payment is updated | H37: 46423.09
G38: (blank) | H38: 28566.52
F39: Quirin Nieuwenhuizen Total | H39: 183297.17
F40: Shaira Castillo-Vierneza | G40: to check if payment is updated | H40: 28645.24
F41: Shaira Castillo-Vierneza Total | H41: 28645.24
F42: (blank) | G42: JPA | H42: 3729562.3
G43: VNG | H43: 221217.56
F44: (blank) Total | H44: 3950779.9
F45: Grand Total | H45: 4381621.8
